madstory_core/__init__.py
madstory_core/element.py
madstory_core/manager.py
madstory_core/scene.py
madstory_core/story.py
madstory_core-0.0.9.dist-info/METADATA
madstory_core-0.0.9.dist-info/WHEEL
madstory_core-0.0.9.dist-info/top_level.txt
madstory_core-0.0.9.dist-info/RECORD
