Metadata-Version: 2.1
Name: madstory-core
Version: 0.0.9
Summary: Core library for the MadStory storytelling platform
Author: Shariq Torres
Author-email: shariq.torres@gmail.com
